{
  "title": "Reverse Engineering program written in Python, compiled with “freeze 2 [REWRITE] [closed]",
  "link": "https://reverseengineering.stackexchange.com/questions/11459/reverse-engineering-program-written-in-python-compiled-with-freeze-2-rewrite",
  "content": "I am already aware of the question: 'Reverse Engineering program written in Python, compiled with “freeze”'\n\nI have Immunity Debugger and is this the pyc code and the structures?\n\n\n\nWhen I run the PyCommand mentioned in the original question, it doesn't dump the pyc code and do not make PYC files. And, I have the PythonMagic Code Correct (Python 2.4). \n\nAny help?\n\n",
  "votes": "1",
  "answers": 0,
  "views": "664",
  "tags": [
    "decompilation",
    "python"
  ],
  "user": "Prince Frizzy",
  "time": "9 years ago",
  "comments": [],
  "answers_data": []
}