{
  "title": "Identifying a hash function knowing both input and output",
  "link": "https://reverseengineering.stackexchange.com/questions/31626/identifying-a-hash-function-knowing-both-input-and-output",
  "content": "I am creating a custom client for an old game. Now I got stuck on login to the server. I made several experiments with wireshark but it doesn't seem to be any common hashes.\nFrom my limited understanding, it doesn't seem to be salted because the same input gets the same output even if I change my account, device, ip...\nHere are some inputs and outputs:\n\n00000 - 5a5ef2\n\n000000 - 9a5af4\n\n0000000 - daacf7\n\n11111 - 763443\n\n01010 - 0660bf\n\n22222 - 82eff1\n\n123123123123 - 368188\n\npassword - 8606df\n\n☺☺☺☺☺ - e27952\n\n",
  "votes": "3",
  "answers": 0,
  "views": "58",
  "tags": [
    "hash-functions"
  ],
  "user": "Luigi Pinnilici",
  "time": "Mar 4, 2023 at 18:14",
  "comments": [],
  "answers_data": []
}