{
    "title": "Where can I get reliable tools for RE?",
    "link": "https://reverseengineering.stackexchange.com/questions/2427/where-can-i-get-reliable-tools-for-re",
    "content": "<div class=\"s-prose js-post-body\" itemprop=\"text\">\n<p>I am looking for a reliable source to download RE tools such as:</p>\n<ol>\n<li>Lordpe</li>\n<li>Imprec</li>\n<li>Peid</li>\n</ol>\n<p>but it seems all the links in google are not safe, where can I buy or download it from a reliable not malwared source. Can I trust <a href=\"http://www.woodmann.com/\">http://www.woodmann.com/</a> ?</p>\n</div>",
    "votes": "8",
    "answers": 3,
    "views": "2k",
    "tags": [
        "tools"
    ],
    "user": "0x90",
    "time": "Dec 3, 2013 at 1:12",
    "comments": [
        {
            "user": "PhoeniX",
            "text": "<span class=\"comment-copy\">Hi,  I've been using woodmann resources for some time and I find it one of the most valuable places not only for RE tools but also for its vast knowledge database of many aspects of RE. So, I think you can trust this resource and use it solve you problems and enrich your knowledge.</span>",
            "time": null
        },
        {
            "user": "Stolas",
            "text": "<span class=\"comment-copy\">Little note: there is a known POC Denial of Service for PEiD. As PEiD is no longer being developed and this issue won't get patched I'd recommend to look for another tool that does the same thing. It's just a matter of time till this public DoS Exploit gets used in the wild. <a href=\"http://www.exploit-db.com/exploits/26413/\" rel=\"nofollow noreferrer\">exploit-db.com/exploits/26413</a></span>",
            "time": null
        },
        {
            "user": "alexanderh",
            "text": "<span class=\"comment-copy\">I have been using Woodmann for years and I have never had issues. Most of these tools you should be running a VM or safe environment anyways. The RCE tools has a large <a href=\"http://www.woodmann.com/collaborative/tools/index.php/Category:RCE_Tools\" rel=\"nofollow noreferrer\">woodmann.com/collaborative/tools/index.php/Category:RCE_Tools</a></span>",
            "time": null
        }
    ],
    "answers_data": [
        {
            "content": "<div class=\"s-prose js-post-body\" itemprop=\"text\">\n<p>Tools archived on <a href=\"http://www.woodmann.com/\">http://www.woodmann.com/</a> should be safe.</p>\n<p>I've personally met and trust most of the people who run the site (Woodmann, dELTA, etc.), and can vouch for their integrity.</p>\n</div>",
            "votes": "20",
            "user": "Jason Geffner",
            "time": "Jul 7, 2013 at 22:01",
            "is_accepted": true,
            "comments": []
        },
        {
            "content": "<div class=\"s-prose js-post-body\" itemprop=\"text\">\n<div>\n<aside class=\"s-notice s-notice__info post-notice js-post-notice mb16\" role=\"status\">\n<div class=\"d-flex fd-column fw-nowrap\">\n<div class=\"d-flex fw-nowrap\">\n<div class=\"flex--item mr8\">\n<svg aria-hidden=\"true\" class=\"svg-icon iconLightbulb\" height=\"18\" viewbox=\"0 0 18 18\" width=\"18\"><path d=\"M15 6.38A6.5 6.5 0 0 0 7.78.04h-.02A6.5 6.5 0 0 0 2.05 5.6a6.3 6.3 0 0 0 2.39 5.75c.49.39.76.93.76 1.5v.24c0 1.07.89 1.9 1.92 1.9h2.75c1.04 0 1.92-.83 1.92-1.9v-.2c0-.6.26-1.15.7-1.48A6.3 6.3 0 0 0 15 6.37M4.03 5.85A4.5 4.5 0 0 1 8 2.02a4.5 4.5 0 0 1 5 4.36 4.3 4.3 0 0 1-1.72 3.44c-.98.74-1.5 1.9-1.5 3.08v.1H7.2v-.14c0-1.23-.6-2.34-1.53-3.07a4.3 4.3 0 0 1-1.64-3.94M10 18a1 1 0 0 0 0-2H7a1 1 0 1 0 0 2z\"></path></svg>\n</div>\n<div class=\"flex--item wmn0 fl1 lh-lg\">\n<div class=\"flex--item fl1 lh-lg\">\n<div>\n<b>Want to improve this post?</b> Provide detailed answers to this question, including citations and an explanation of why your answer is correct. Answers without enough detail may be edited or deleted.\n                                \n                            </div>\n</div>\n</div>\n</div>\n</div>\n</aside>\n</div>\n<p>There is also the option of <a href=\"http://www.tuts4you.com\">tuts4you</a>. They have an extensive download page there.</p>\n</div>",
            "votes": "7",
            "user": "gandolf",
            "time": "Jul 9, 2013 at 16:24",
            "is_accepted": false,
            "comments": []
        },
        {
            "content": "<div class=\"s-prose js-post-body\" itemprop=\"text\">\n<div>\n<aside class=\"s-notice s-notice__info post-notice js-post-notice mb16\" role=\"status\">\n<div class=\"d-flex fd-column fw-nowrap\">\n<div class=\"d-flex fw-nowrap\">\n<div class=\"flex--item mr8\">\n<svg aria-hidden=\"true\" class=\"svg-icon iconLightbulb\" height=\"18\" viewbox=\"0 0 18 18\" width=\"18\"><path d=\"M15 6.38A6.5 6.5 0 0 0 7.78.04h-.02A6.5 6.5 0 0 0 2.05 5.6a6.3 6.3 0 0 0 2.39 5.75c.49.39.76.93.76 1.5v.24c0 1.07.89 1.9 1.92 1.9h2.75c1.04 0 1.92-.83 1.92-1.9v-.2c0-.6.26-1.15.7-1.48A6.3 6.3 0 0 0 15 6.37M4.03 5.85A4.5 4.5 0 0 1 8 2.02a4.5 4.5 0 0 1 5 4.36 4.3 4.3 0 0 1-1.72 3.44c-.98.74-1.5 1.9-1.5 3.08v.1H7.2v-.14c0-1.23-.6-2.34-1.53-3.07a4.3 4.3 0 0 1-1.64-3.94M10 18a1 1 0 0 0 0-2H7a1 1 0 1 0 0 2z\"></path></svg>\n</div>\n<div class=\"flex--item wmn0 fl1 lh-lg\">\n<div class=\"flex--item fl1 lh-lg\">\n<div>\n<b>Want to improve this post?</b> Provide detailed answers to this question, including citations and an explanation of why your answer is correct. Answers without enough detail may be edited or deleted.\n                                \n                            </div>\n</div>\n</div>\n</div>\n</div>\n</aside>\n</div>\n<p>There is also <a href=\"http://www.openrce.org/downloads/\" rel=\"nofollow\">http://www.openrce.org/downloads/</a>\nThough it does not have specific tools you are looking for, it has lots of plugins for IDA and OllyDbg. It is trustworthy source as well.</p>\n</div>",
            "votes": "4",
            "user": "PSS",
            "time": "Jul 10, 2013 at 14:12",
            "is_accepted": false,
            "comments": []
        }
    ]
}