{
    "title": "How does this levitating clock work?",
    "link": "https://reverseengineering.stackexchange.com/questions/24964/how-does-this-levitating-clock-work",
    "content": "<div class=\"s-prose js-post-body\" itemprop=\"text\">\n<p>I came across the Flyte STORY clock recently (<a href=\"https://flytestore.com/pages/story-levitating-timepiece\" rel=\"nofollow noreferrer\">link</a>) and I’m stumped as to how it works.\nDoes anyone know how it holds the ball against gravity when it’s vertically upright?</p>\n<p><a href=\"https://i.sstatic.net/05jrP.jpg\" rel=\"nofollow noreferrer\"><img alt=\"enter image description here\" src=\"https://i.sstatic.net/05jrP.jpg\"/></a></p>\n<p>I asked Physics but they closed the question immediately. Hopefully this is the right place to ask!</p>\n<p><a href=\"https://hackaday.com/2017/02/26/howd-they-do-it-levitating-orb-clock/\" rel=\"nofollow noreferrer\">This article</a> touches on the subject, but provided only speculation and no detail.</p>\n</div>",
    "votes": "2",
    "answers": 1,
    "views": "517",
    "tags": [
        "hardware"
    ],
    "user": "Michael Finn",
    "time": "Feb 7, 2023 at 9:28",
    "comments": [
        {
            "user": "auspicious99",
            "text": "<span class=\"comment-copy\">Sorry, I don't think this is the right place to ask, either.</span>",
            "time": null
        },
        {
            "user": "Michael Finn",
            "text": "<span class=\"comment-copy\">@auspicious99 Can you suggest a different forum?</span>",
            "time": null
        },
        {
            "user": "hippietrail",
            "text": "<span class=\"comment-copy\">@MichaelFinn: You can try Quora, they don't have the stringent rules of Stack Exchanges, but sometimes some questions don't get noticed.</span>",
            "time": null
        },
        {
            "user": "Michael Finn",
            "text": "<span class=\"comment-copy\">@hippietrail Thanks for the advice! I’ll leave this up in case a kind stranger feels like imparting wisdom, but no hard feelings if it needs to be closed.</span>",
            "time": null
        },
        {
            "user": "Robert",
            "text": "<span class=\"comment-copy\">Flyte uses <a href=\"https://en.wikipedia.org/wiki/Magnetic_levitation\" rel=\"nofollow noreferrer\">Magnetic levitation</a> in other products. Hence most likely it is used here, too. There is a <a href=\"https://www.tugraz.at/fileadmin/user_upload/Institute/IEP/Thermophysics_Group/Files/Teachers/Diplomarbeit_Stefan_Leitner.pdf\" rel=\"nofollow noreferrer\">thesis (German language)</a> describing it (scroll to \"Flyte\" section)</span>",
            "time": null
        }
    ],
    "answers_data": [
        {
            "content": "<div class=\"s-prose js-post-body\" itemprop=\"text\">\n<p><strong>Briefly:</strong></p>\n<p>inside the clock:\n<a href=\"https://i.sstatic.net/Hj3MU.jpg\" rel=\"nofollow noreferrer\"><img alt=\"enter image description here\" src=\"https://i.sstatic.net/Hj3MU.jpg\"/></a></p>\n<p><strong>Full manufacturing instructions:</strong></p>\n<p><a href=\"https://www.instructables.com/Mesmerizing-Magnetic-Wall-Clock/\" rel=\"nofollow noreferrer\">https://www.instructables.com/Mesmerizing-Magnetic-Wall-Clock/</a></p>\n<p><a href=\"https://web.archive.org/web/20201228064243/https://www.instructables.com/Mesmerizing-Magnetic-Wall-Clock\" rel=\"nofollow noreferrer\">webarchived</a></p>\n</div>",
            "votes": "2",
            "user": null,
            "time": "Dec 25, 2022 at 23:05",
            "is_accepted": false,
            "comments": [
                {
                    "user": "Michael Finn",
                    "text": "<span class=\"comment-copy\">Unfortunately this DIY project does not appear to levitate the ball, but rather holds it magnetically against the side of the clock face. I do appreciate the answer attempt almost three years later, though!</span>",
                    "time": null
                }
            ]
        }
    ]
}