{
    "title": "format-string + ret2libc (or format string only)?",
    "link": "https://reverseengineering.stackexchange.com/questions/31402/format-string-ret2libc-or-format-string-only",
    "content": "<div class=\"s-prose js-post-body\" itemprop=\"text\">\n<p>I found that we have a format-string bug with in argument 7. I found a function containing system(<code>/bin/sh</code>)). So I'm not saying stupidity I have to mess with a format-string and a <code>ret2libc</code> (correct me if I'm wrong). I don't know how to exploit it, can you help me?</p>\n<p><em>Images: Ghidra and GDB</em></p>\n<p><a href=\"https://i.sstatic.net/P6wPe.png\" rel=\"nofollow noreferrer\"><img alt=\"system function\" src=\"https://i.sstatic.net/P6wPe.png\"/></a></p>\n<p><a href=\"https://i.sstatic.net/Aov7H.png\" rel=\"nofollow noreferrer\"><img alt=\"entry function\" src=\"https://i.sstatic.net/Aov7H.png\"/></a></p>\n<p><a href=\"https://i.sstatic.net/66sbf.png\" rel=\"nofollow noreferrer\"><img alt=\"all functions on gdb\" src=\"https://i.sstatic.net/66sbf.png\"/></a></p>\n</div>",
    "votes": "3",
    "answers": 0,
    "views": "149",
    "tags": [
        "ghidra",
        "gdb",
        "exploit"
    ],
    "user": "98m16",
    "time": "Jan 24, 2023 at 8:48",
    "comments": [],
    "answers_data": []
}