{
    "title": "Why i cant see source code from this dll",
    "link": "https://reverseengineering.stackexchange.com/questions/31714/why-i-cant-see-source-code-from-this-dll",
    "content": "<div class=\"s-prose js-post-body\" itemprop=\"text\">\n<p>// PE file does not contain any managed metadata.\n<a href=\"https://i.sstatic.net/3B4NZ.png\" rel=\"nofollow noreferrer\"><img alt=\"enter image description here\" src=\"https://i.sstatic.net/3B4NZ.png\"/></a></p>\n</div>",
    "votes": "2",
    "answers": 0,
    "views": "268",
    "tags": [
        "decompilation"
    ],
    "user": "Zeko It",
    "time": "Mar 25, 2023 at 22:28",
    "comments": [
        {
            "user": "Robert",
            "text": "<span class=\"comment-copy\">If I understand the message correctly. then this means the DLL is not a .NET DLL and thus can not be decompiled using ILSpy. You need to use a tool like Ghidra or IDA (Pro) to decompile it, but be aware that decompiling non dot net DLLs is much harder, thus the decompiled code will much harder to read and some times even be wrong.</span>",
            "time": null
        }
    ],
    "answers_data": []
}