{
    "title": "How to restore IAT?",
    "link": "https://reverseengineering.stackexchange.com/questions/21924/how-to-restore-iat",
    "content": "<html><body><div class=\"s-prose js-post-body\" itemprop=\"text\">\n <p>\n  I have the start address and the end address of the IAT\nnow im trying to restore the table/folder of it.\nthe start address is: E7C000\nthx for helping\n  <a href=\"https://i.sstatic.net/I4iCE.png\" rel=\"nofollow noreferrer\">\n   <img alt=\"enter image description here\" src=\"https://i.sstatic.net/I4iCE.png\"/>\n  </a>\n </p>\n</div>\n</body></html>",
    "votes": "2",
    "answers": 1,
    "views": "620",
    "tags": [
        "ida",
        "pe",
        "static-analysis",
        "pe-resources"
    ],
    "user": "Yoni",
    "time": "Aug 18, 2019 at 13:47",
    "comments": [
        {
            "user": "NirIzr",
            "text": "<html><body><span class=\"comment-copy\">\n Welcome to RE.SE! If this is part of an unpacking effort it may be a bit more complicated than what you seem to be expecting. Providing more information in your question may be helpful here.\n</span>\n</body></html>",
            "time": null
        }
    ],
    "answers_data": [
        {
            "content": "<html><body><div class=\"s-prose js-post-body\" itemprop=\"text\">\n <p>\n  I used\n  <a href=\"https://ntcore.com/?page_id=388\" rel=\"nofollow noreferrer\">\n   Explorer Suite\n  </a>\n  for patching IAT.\n </p>\n</div>\n</body></html>",
            "votes": "-1",
            "user": "0xC0000022L",
            "time": "May 18, 2020 at 19:20",
            "is_accepted": false,
            "comments": [
                {
                    "user": "0xC0000022L",
                    "text": "<span class=\"comment-copy\">While this may answer the question, it's a bit thin on the details. It would be nice if you could flesh that out a bit, for example with a screenshot showing what to change where ...</span>",
                    "time": null
                },
                {
                    "user": "slinkin",
                    "text": "<span class=\"comment-copy\">To be honest, it seems I was wrong when answered the question. I used Explorer Suite for adding new libs and changing addresses of some functions. At the same time, the question implies restoring the original Import Table after deobfuscation.</span>",
                    "time": null
                },
                {
                    "user": "Mega Tonnage",
                    "text": "<span class=\"comment-copy\">I'd usually go with LordPE to rebuild the IAT, it doesn't need a lot of help.</span>",
                    "time": null
                },
                {
                    "user": "Rohit Gupta",
                    "text": "<span class=\"comment-copy\">@slinkin - If you were wrong about it, then perhaps you should delete the answer before it gets downvotes</span>",
                    "time": null
                },
                {
                    "user": "Mega Tonnage",
                    "text": "<span class=\"comment-copy\">@0xC0000022L  .. no, I haven't come across any, but there are many projects out there on GH etc so it wouldn't surprise me.</span>",
                    "time": null
                }
            ]
        }
    ]
}