{
    "title": "How do I permanently change the disassembly syntax in Radare2?",
    "link": "https://reverseengineering.stackexchange.com/questions/23332/how-do-i-permanently-change-the-disassembly-syntax-in-radare2",
    "content": "<html><body><div class=\"s-prose js-post-body\" itemprop=\"text\">\n <p>\n  As the title says, I am trying to change the default disassembly syntax in Radare2 from Intel to AT&T. Looking up documentation, I found the following.\n </p>\n <pre><code>[0x00405e1c]> e asm.syntax=att\n</code></pre>\n <p>\n  However, changing syntax this way does not persist across sessions. Is there a command I can use to save settings permanently?\n </p>\n</div>\n</body></html>",
    "votes": "4",
    "answers": 1,
    "views": "2k",
    "tags": [
        "radare2"
    ],
    "user": "peachykeen",
    "time": "Feb 24, 2020 at 15:27",
    "comments": [],
    "answers_data": [
        {
            "content": "<html><body><div class=\"s-prose js-post-body\" itemprop=\"text\">\n <p>\n  From\n  <code>\n   Radare2\n  </code>\n  <a href=\"https://radare.gitbooks.io/radare2book/configuration/intro.html\" rel=\"noreferrer\">\n   book\n  </a>\n  :\n </p>\n <blockquote>\n  <p>\n   The core reads\n   <code>\n    ~/.config/radare2/radare2rc\n   </code>\n   while starting. You can add\n   <code>\n    e\n   </code>\n   commands to this file to tune the radare2 configuration to your\n  taste.\n  </p>\n </blockquote>\n</div>\n</body></html>",
            "votes": "6",
            "user": "perror",
            "time": "Feb 24, 2020 at 16:49",
            "is_accepted": true,
            "comments": []
        }
    ]
}