{
    "title": "CAN checksum algorithm",
    "link": "https://reverseengineering.stackexchange.com/questions/26171/can-checksum-algorithm",
    "content": "<html><body><div class=\"s-prose js-post-body\" itemprop=\"text\">\n <p>\n  I am trying to caclulate a checksum algorithm. D0 is CRC, D1 to D2 is data. Maybe someone can help me with algorithm for checksum calculation?\n </p>\n <pre><code>D0  D1  D2  D3\n68  00  01  00\n74  00  03  00\nDD  01  01  00\nC1  01  03  00\n2D  02  01  00\n31  02  03  00\n98  03  01  00\n84  03  03  00\nE2  04  01  00\nFE  04  03  00\n57  05  01  00\n4B  05  03  00\nA7  06  01  00\nBB  06  03  00\n12  07  01  00\n0E  07  03  00\n53  08  01  00\n4F  08  03  00\nE6  09  01  00\nFA  09  03  00\n16  0A  01  00\n0A  0A  03  00\nA3  0B  01  00\nBF  0B  03  00\nD9  0C  01  00\nC5  0C  03  00\n6C  0D  01  00\n70  0D  03  00\n9C  0E  01  00\n80  0E  03  00\n</code></pre>\n</div>\n</body></html>",
    "votes": "1",
    "answers": 1,
    "views": "193",
    "tags": [
        "crc"
    ],
    "user": "Pablo",
    "time": "Oct 24, 2020 at 18:47",
    "comments": [
        {
            "user": "Robert",
            "text": "<html><body><span class=\"comment-copy\">\n In your title you mentioned \"CAN\". If you are referring to the well known\n <a href=\"https://en.wikipedia.org/wiki/CAN_bus\" rel=\"nofollow noreferrer\">\n  CAN-bus\n </a>\n have you checked it's documentation where the used CRC method is described?\n</span>\n</body></html>",
            "time": null
        }
    ],
    "answers_data": [
        {
            "content": "<html><body><div class=\"s-prose js-post-body\" itemprop=\"text\">\n <p>\n  If you have more messages you could try this for reverse engineering checksums:\n  <a href=\"https://github.com/laurenlabell/checksum_finder\" rel=\"nofollow noreferrer\">\n   https://github.com/laurenlabell/checksum_finder\n  </a>\n </p>\n <p>\n  For CRCs there's a tool called CRCRevEng which is harder to use, but can tackle CRCs.\n </p>\n</div>\n</body></html>",
            "votes": "1",
            "user": "pythonpython",
            "time": "Nov 23, 2020 at 1:23",
            "is_accepted": false,
            "comments": []
        }
    ]
}