{
    "title": "How to get the call stack of WinAPI functions?",
    "link": "https://reverseengineering.stackexchange.com/questions/30778/how-to-get-the-call-stack-of-winapi-functions",
    "content": "<html><body><div class=\"s-prose js-post-body\" itemprop=\"text\">\n <p>\n  Yesterday, I noticed an\n  <a href=\"https://reverseengineering.stackexchange.com/a/19238/40872\">\n   answer\n  </a>\n  to a question about the purpose of a certain undocumented function, which is a call stack (including the DLL library) for this function, This got me interested in the approachs in this matter!\n </p>\n <p>\n  How to get the WinAPI function's\n  <strong>\n   call stack\n  </strong>\n  and which\n  <strong>\n   DLL libraries\n  </strong>\n  that have the function there ? and is there a way to find out all of that\n  <strong>\n   statically\n  </strong>\n  without the debugger ?\n </p>\n</div>\n</body></html>",
    "votes": "1",
    "answers": 0,
    "views": "136",
    "tags": [
        "windows",
        "debugging",
        "static-analysis",
        "dynamic-analysis",
        "winapi"
    ],
    "user": "IVs",
    "time": "Aug 14, 2022 at 17:15",
    "comments": [],
    "answers_data": []
}