{
    "title": "how to reverse DeviceIoControl?",
    "link": "https://reverseengineering.stackexchange.com/questions/3955/how-to-reverse-deviceiocontrol",
    "content": "<html><body><div class=\"s-prose js-post-body\" itemprop=\"text\">\n <p>\n  I have started reversing this piece of malware. At some point it creates a service and starts it, then immediately it calls the function\n  <code>\n   DeviceIoControl\n  </code>\n  and the malware went from \"paused\" to \"running\" under ollydbg. I've searched a little bit, and I understand that this function serves to communicate with the service it just had created.\n </p>\n <p>\n  But how exactly do I reverse it? How do I know what it does? And how can I continue stepping under ollydbg? Or do I have to move to windbg or some other kernel-mode debugger?\n </p>\n</div>\n</body></html>",
    "votes": "5",
    "answers": 2,
    "views": "4k",
    "tags": [
        "malware",
        "kernel-mode"
    ],
    "user": "user4170",
    "time": "Mar 26, 2014 at 7:13",
    "comments": [],
    "answers_data": [
        {
            "content": "<html><body><div class=\"s-prose js-post-body\" itemprop=\"text\">\n <p>\n  You cannot step into kernel mode from Ollydbg. You need a kernel debugger like\n  <code>\n   windbg\n  </code>\n  , as\n  <code>\n   ollydbg\n  </code>\n  is a user mode debugger.\n </p>\n <p>\n  Since you posed the question, I assume you neither have a kernel debugging connection,\nnor the driver where that control code is sent for analyzing it, as answered by Jonathon.\n </p>\n <p>\n  Usage of proper security measures to deal with malware assumed and emphasized from here onward.\n </p>\n <p>\n  I assume the malware is running already as your query states that you are on\n  <code>\n   DeviceIoControl\n  </code>\n  .\n </p>\n <p>\n  I am going to use ollydbg 2.01.\n </p>\n <p>\n  Attach ollydbg to an unknown process\n </p>\n <p>\n  Press\n  <kbd>\n   Ctrl\n  </kbd>\n  +\n  <kbd>\n   G\n  </kbd>\n  and start typing\n  <code>\n   ntdll.ntDeviceIo\n  </code>\n  and the list box  will show\n  <code>\n   ntdll.ntDeviceIoControl\n  </code>\n  now  select it and\n  <code>\n   follow label\n  </code>\n  .\n </p>\n <p>\n  Press\n  <kbd>\n   F2\n  </kbd>\n  to set a breakpoint, and\n  <kbd>\n   F9\n  </kbd>\n  to run the attached process.\n </p>\n <pre><code>INT3 breakpoints, item 0\n  Address = 7C90D27E NtDeviceIoControlFile\n  Module = ntdll\n  Status = Active\n  Disassembly = MOV     EAX, 42\n  Comment = ntdll.NtDeviceIoControlFile(guessed Arg1,Arg2,Arg3,Arg4,Arg5,Arg6,Arg7,Arg8,Arg9,Arg10)\n</code></pre>\n <p>\n  Ollydbg should break when a control code is sent and stack should look like this:\n </p>\n <pre><code>CPU Stack\n    Address   Value      ASCII Comments\n    0013EF50  [7C801675  u€|   ; /RETURN from ntdll.NtDeviceIoControlFile to kernel32.DeviceIoControl+4C\n    0013EF54  /00000090        ; |Arg1 = 90\n    0013EF58  |00000000        ; |Arg2 = 0\n    0013EF5C  |00000000        ; |Arg3 = 0\n    0013EF60  |00000000        ; |Arg4 = 0\n    0013EF64  |0013EF88  ˆï    ; |Arg5 = 13EF88\n    0013EF68  |83050024  $ ƒ   ; |Arg6 = 83050024\n    0013EF6C  |00000000        ; |Arg7 = 0\n    0013EF70  |00000000        ; |Arg8 = 0\n    0013EF74  |0013EFEC  ìï    ; |Arg9 = 13EFEC\n    0013EF78  |00000004        ; \\Arg10 = 4\n</code></pre>\n <p>\n  From the specs of\n  <code>\n   DeviceIoControlCode\n  </code>\n  , the first argument points to\n  <code>\n   handle\n  </code>\n  and the sixth argument is the\n  <code>\n   control code\n  </code>\n </p>\n <p>\n  Having windbg installed can make things easier from here, but we will not use windbg at this moment as it has a steep learning curve.\n </p>\n <p>\n  Open ollydbg handle window and find what does the handle point to (\n  <code>\n   0x90\n  </code>\n  in the above paste) - it points to a device:\n </p>\n <pre><code>Handles, item 9\n  Handle = 00000090\n  Type = File (dev)   <-------- it is a _FILE_OBJECT\n  Refs =    2.\n  Access = 0012019F (FILE_GENERIC_READ|FILE_GENERIC_WRITE)\n  Tag =\n  Info =\n  Translated name = \\Device\\Dbgv\n</code></pre>\n <p>\n  Now run\n  <a href=\"http://technet.microsoft.com/en-us/sysinternals/bb896653.aspx\" rel=\"noreferrer\">\n   Process Explorer\n  </a>\n  from\n  <code>\n   SysInternals\n  </code>\n  . Select the unknown process, and press\n  <kbd>\n   Ctrl\n  </kbd>\n  +\n  <kbd>\n   H\n  </kbd>\n  to make the lower pane show handles.\n </p>\n <p>\n  Select the handle\n  <code>\n   90\n  </code>\n  , right click and select\n  <code>\n   properties\n  </code>\n  .\n  <em>\n   Process Explorer\n  </em>\n  will show the address of the\n  <em>\n   Device Object\n  </em>\n  as noted by Ollydbg. This device object is a\n  <em>\n   File Object\n  </em>\n  :\n </p>\n <p>\n  <img alt=\"enter image description here\" src=\"https://i.sstatic.net/ZFEXl.png\"/>\n </p>\n <p>\n  <code>\n   ollydbg 2.01\n  </code>\n  can show memory above\n  <code>\n   0x7fffffff\n  </code>\n  (kernel mode memory) we will use that feature to find the driver associated with this device\n </p>\n <p>\n  Read about the\n  <a href=\"http://msdn.microsoft.com/en-us/library/windows/hardware/ff545834.aspx\" rel=\"noreferrer\">\n   <code>\n    FILE_OBJECT\n   </code>\n  </a>\n  structure relevant to your OS. In Windows XP you will find the address of device object at +4 from file object.\n </p>\n <p>\n  Select the dump window press\n  <kbd>\n   Ctrl\n  </kbd>\n  +\n  <kbd>\n   G\n  </kbd>\n  and type in the address process explorer showed viz\n </p>\n <pre><code>863c87f0 and follow expression \n\nCPU Dump\nAddress   Hex dump                                         ASCII\n863C87F0  05 00 70 00|A8 D3 51 86|00 00 00 00|00 00 00 00|  p ¨ÓQ†\n</code></pre>\n <p>\n  So\n  <code>\n   8651d3a8\n  </code>\n  in the paste above points to the device object for this file object.\n </p>\n <p>\n  Read about\n  <a href=\"http://msdn.microsoft.com/en-us/library/windows/hardware/ff543147.aspx\" rel=\"noreferrer\">\n   <code>\n    DEVICE_OBJECT\n   </code>\n  </a>\n  structure.  In Windows XP, the address of the driver object is at device object + 8.  Following there with\n  <kbd>\n   Ctrl\n  </kbd>\n  +\n  <kbd>\n   G\n  </kbd>\n  ->\n  <code>\n   follow expression\n  </code>\n  as done earlier\n </p>\n <pre><code>CPU Dump\nAddress   Hex dump                                         ASCII\n8651D3A8  03 00 B8 00|01 00 00 00|48 2C F1 86|00 00 00 00|  ¸    H,ñ†\n</code></pre>\n <p>\n  notice\n  <code>\n   86f12c48\n  </code>\n  is driver object. Read about\n  <a href=\"http://msdn.microsoft.com/en-us/library/windows/hardware/ff544174.aspx\" rel=\"noreferrer\">\n   <code>\n    DRIVER_OBJECT\n   </code>\n  </a>\n  structure.\n </p>\n <p>\n  <code>\n   +0xc is Driver Start\n  </code>\n  and\n  <code>\n   +0x10 is Driver Size\n  </code>\n  -->\n  <kbd>\n   Ctrl\n  </kbd>\n  +\n  <kbd>\n   G\n  </kbd>\n  to follow:\n </p>\n <pre><code>CPU Dump\nAddress   Hex dump                                         ASCII\n86F12C48  04 00 A8 00|A8 D3 51 86|12 00 00 00|00 30 2A A9|  ¨ ¨ÓQ†    0*©\n86F12C58  00 3D 00 00|48 9C D8 86|F0 2C F1 86|18 00 18 00|  =  HœØ†ð,ñ† \n</code></pre>\n <p>\n  <code>\n   a92a3000\n  </code>\n  is\n  <code>\n   DriverStart\n  </code>\n  and size of driver is\n  <code>\n   3d00\n  </code>\n  .\n </p>\n <p>\n  <kbd>\n   Ctrl\n  </kbd>\n  +\n  <kbd>\n   G\n  </kbd>\n  to follow:\n </p>\n <pre><code>CPU Dump\nAddress   Hex dump                                         ASCII\nA92A3000  4D 5A 90 00|03 00 00 00|04 00 00 00|FF FF 00 00| MZ       ÿÿ\nA92A3010  B8 00 00 00|00 00 00 00|40 00 00 00|00 00 00 00| ¸       @\n</code></pre>\n <p>\n  The famous\n  <code>\n   IMAGE_DOS_HEADER\n  </code>\n  is noticeable.\n </p>\n <p>\n  Select from\n  <code>\n   a92a3000\n  </code>\n  to\n  <code>\n   a92a6d00\n  </code>\n  ,\n  <kbd>\n   Right-Click\n  </kbd>\n  ->\n  <code>\n   Edit\n  </code>\n  -> binary copy and paste the bytes to a new file in any hex editor (HxD for example), and save it as\n  <code>\n   malwaredriver.sys\n  </code>\n  :)\n </p>\n <pre><code>foo:\\>dir malwaredriver.sys\n\n26/03/2014  14:04            15,616 malwaredriver.sys\n\n\\>set /a 0x3d00\n15616\n\\>file malwaredriver.sys\n\nmalwaredriver.sys; PE32 executable for MS Windows (native) Intel 80386 32-bit\n\n:\\>\n</code></pre>\n <p>\n  You can now analyze the driver statically.\n </p>\n <p>\n  Read about\n  <a href=\"http://msdn.microsoft.com/en-us/library/windows/hardware/ff544174.aspx\" rel=\"noreferrer\">\n   <code>\n    DRIVER_OBJECT\n   </code>\n  </a>\n  structure carefully to find you can readily know the handler for\n  <a href=\"http://msdn.microsoft.com/en-us/library/windows/hardware/ff550744.aspx\" rel=\"noreferrer\">\n   <code>\n    IRP_MJ_DEVICE_IO_CONTROL\n   </code>\n  </a>\n  handler in ollydbg. It would be at\n  <code>\n   +0x70\n  </code>\n  from Driverobject in XP. For this particular driver, the\n  <code>\n   IRP_MJ_DEVICE_IO_CONTROL_HANDLER\n  </code>\n  is at\n </p>\n <pre><code>CPU Dump\nAddress   Value      ASCII Comments\n86F12CB8   A92A4168  hA*©\n</code></pre>\n <p>\n  You can follow and disassemble this memory in ollydbg. Select cpu dump press ctrl+g to disassemble an unknown driver\n </p>\n <pre><code>CPU Disasm\nAddress   Command                             Comments\nA92A4168  MOV     EDI, EDI                    ; IRP_MJ_DEVICE_IO_CONTROL_HANDLER(pdevob,pirp)\nA92A416A  PUSH    EBP\nA92A416B  MOV     EBP, ESP\nA92A416D  SUB     ESP, 24\nA92A4170  PUSH    EBX\nA92A4171  PUSH    ESI\nA92A4172  MOV     ESI, DWORD PTR SS:[EBP+0C]  ; irp\nA92A4175  MOV     EAX, DWORD PTR DS:[ESI+60]  ; nt!_irp -y Tail.overlay.cur->maj\nA92A4178  MOV     EDX, DWORD PTR DS:[ESI+0C]  ; nt!_irp Tail.overlay.cur->par.DeviceIo.ty\nA92A417B  XOR     EBX, EBX\nA92A417D  PUSH    EDI\nA92A417E  LEA     EDI, [ESI+18]\nA92A4181  MOV     DWORD PTR DS:[EDI], EBX\nA92A4183  MOV     DWORD PTR DS:[ESI+1C], EBX\nA92A4186  MOVZX   ECX, BYTE PTR DS:[EAX]\nA92A4189  SUB     ECX, EBX\nA92A418B  JE      SHORT A92A41F7              ; case 0 create\nA92A418D  DEC     ECX\nA92A418E  DEC     ECX\nA92A418F  JE      SHORT A92A41CA              ; case 2 close\nA92A4191  SUB     ECX, 0C\nA92A4194  JNE     A92A42BB                    ; unhandled\nA92A419A  MOV     ECX, DWORD PTR DS:[EAX+0C]  ; ioctl\nA92A419D  MOV     EBX, ECX\nA92A419F  AND     EBX, 00000003\nA92A41A2  CMP     BL, 3\nA92A41A5  JNE     SHORT A92A41AC              ; buff align\nA92A41A7  MOV     EBX, DWORD PTR DS:[ESI+3C]\nA92A41AA  JMP     SHORT A92A41AE\nA92A41AC  MOV     EBX, EDX                    ; inbuff\nA92A41AE  PUSH    DWORD PTR SS:[EBP+8]        ; devobj\nA92A41B1  PUSH    EDI\nA92A41B2  PUSH    ECX\nA92A41B3  PUSH    DWORD PTR DS:[EAX+4]        ; bufflen\nA92A41B6  PUSH    EBX\nA92A41B7  PUSH    DWORD PTR DS:[EAX+8]        ; ioctlcode\nA92A41BA  PUSH    EDX\nA92A41BB  PUSH    1\nA92A41BD  PUSH    DWORD PTR DS:[EAX+18]       ; fobj\nA92A41C0  CALL    A92A3EEC                    ; actual_handler\n</code></pre>\n <p>\n  Here the ioctl code is handled:\n </p>\n <pre><code>CPU Disasm\nAddress   Command                                  Comments\nA92A3EF8  MOV     ESI, DWORD PTR SS:[EBP+24]\nA92A3EFB  XOR     EBX, EBX\nA92A3EFD  MOV     DWORD PTR DS:[ESI], EBX\nA92A3EFF  MOV     DWORD PTR DS:[ESI+4], EBX\nA92A3F02  MOV     ECX, DWORD PTR SS:[EBP+20]\nA92A3F05  MOV     EAX, 83050020\nA92A3F0A  CMP     ECX, EAX\nA92A3F0C  JA      A92A40F1  this code will take this path as 24 > 20\n</code></pre>\n <p>\n  ===========\n </p>\n <pre><code>CPU Disasm\nAddress     Hex dump                  Command                Comments\nA92A40F1    81F9 24000583             CMP     ECX, 83050024\nA92A40F7    74 3F                     JE      SHORT A92A4138 path taken\n</code></pre>\n <p>\n  The control code does this work and sends some 320 on some condition\n </p>\n <pre><code>[code]\nCPU Disasm\nAddress   Command                             Comments\nA92A4138  PUSH    4\nA92A413A  POP     EAX\nA92A413B  CMP     DWORD PTR SS:[EBP+1C], EAX\nA92A413E  JB      SHORT A92A4152\nA92A4140  MOV     ECX, DWORD PTR SS:[EBP+18]\nA92A4143  CMP     ECX, EBX\nA92A4145  JE      SHORT A92A4152\nA92A4147  MOV     DWORD PTR DS:[ECX], 320      <------------\nA92A414D  MOV     DWORD PTR DS:[ESI+4], EAX\nA92A4150  JMP     SHORT A92A4158\nA92A4152  MOV     DWORD PTR DS:[ESI], C000000D\nA92A4158  MOV     AL, 1\nA92A415A  CALL    A92A46D5\nA92A415F  RETN    24\n</code></pre>\n <p>\n  The driver analysed here is the driver loaded by dbgview (dbgv.sys) from SysInternals. This control code checks for an incompatible version of driver loaded in memory. Follow through can be practiced with the specific driver and specific version:\n </p>\n <pre><code>(4.75) build time Thu Aug 07 04:51:27 2008\n</code></pre>\n <h2>\n  EDIT\n </h2>\n <p>\n  With windbg inastalled you can do the same with just few commands as posted below\n </p>\n <pre><code>C:\\>tlist | grep -i dbgview\n\n3724 Dbgview.exe       DebugView on \\\\ (local)\n\nC:\\>kd -kl -c \".foreach /pS 1 /ps 4 (place  { .shell -ci \\\"!handle 0 3 0n3724 Fi\nle \\\" grep File } ) {dt nt!_FILE_OBJECT -y Dev->Dri->DriverS place};q\" | grep -i\n +0x00c\n +0x00c DriverStart       : 0xf7451000 Void  \n +0x00c DriverStart       : 0xf73c5000 Void   \n +0x00c DriverStart       : 0xa87f9000 Void   \n +0x00c DriverStart       : 0xf7451000 Void   \n +0x00c DriverStart       : 0xf7451000 Void   \n\nC:\\>kd -kl -c \".reload ; lm a (0xf7451000); lm a (0xf73c5000) ; lm a (0xa87f9000);q\" | grep -i defer\n\n f7451000 f746f880   ftdisk     (deferred)    \n f73c5000 f73db880   KSecDD     (deferred)    \n a87f9000 a87fcd00   Dbgv       (deferred)    \n\n\nC:\\>kd -kl -c \".writemem  malware.sys a87f9000 a87fcfff ;q\" | grep -A 1 lkd\n\n lkd> kd: Reading initial command '.writemem  malware.sys a87f9000 a87fcfff ;q'     \n Writing 4000 bytes........    \n\nC:\\>file malware.sys  \n\n malware.sys; PE32 executable for MS Windows (native) Intel 80386 32-bit   \n</code></pre>\n <p>\n  An explanation for the commands above as follows\n </p>\n <pre><code>kd -kl is local kernel debugging\n\n!handle command has the capability to search for kernel handle  \nwhen you input a Pid \n\nThe explanation for arguments for this commands are \n\n 0 = all handles \n 3 = default flag provides basic+object information\n 0n3724 = pid (can be from task manager\n File = type of Object to search for \n\n\n!dt can display memebers of nested structures with ease \n-y with dt takes partial inputs (wild card entries ) \n and displays  all matching structure members \n\nand the output is manipulatable with any text / stream handling \nsoftware like grep , sed . awk . find etc\n</code></pre>\n</div>\n</body></html>",
            "votes": "15",
            "user": "perror",
            "time": "Apr 12, 2014 at 7:44",
            "is_accepted": true,
            "comments": [
                {
                    "user": "fileoffset",
                    "text": "<span class=\"comment-copy\">Lot's of good tips here!</span>",
                    "time": null
                }
            ]
        },
        {
            "content": "<html><body><div class=\"s-prose js-post-body\" itemprop=\"text\">\n <p>\n  More specifically, it sounds like your executable is loading a Device Driver.  Userspace executables often communicates with drivers via\n  <a href=\"http://en.wikipedia.org/wiki/Ioctl\" rel=\"nofollow noreferrer\">\n   IOCTLs\n  </a>\n  (or I/O Controls).\n </p>\n <p>\n  <a href=\"http://msdn.microsoft.com/en-us/library/windows/desktop/aa363216.aspx\" rel=\"nofollow noreferrer\">\n   <code>\n    DeviceIoControl\n   </code>\n  </a>\n  does just that: sends an IOCTL to the driver.  Note the second parameter to this function:\n  <code>\n   DWORD dwIoControlCode\n  </code>\n  .  This is the code that identifies which IOCTL the program is requesting the driver to perform.  It is just a 32-bit DWORD value.\n </p>\n <p>\n  Now, on the driver side there are a few things you need to know.\n  <sub>\n   (Be prepared to swim through a few structures!)\n  </sub>\n </p>\n <p>\n  When a driver is first loaded, its\n  <code>\n   DriverEntry\n  </code>\n  function will be called. This is passed a pointer to the driver's\n  <a href=\"http://msdn.microsoft.com/en-us/library/windows/hardware/ff544174.aspx\" rel=\"nofollow noreferrer\">\n   <code>\n    DRIVER_OBJECT\n   </code>\n  </a>\n  .  In this structure there is an array named\n  <code>\n   MajorFunction\n  </code>\n  , which is a set of function pointers that the kernel will call when userspace tries to do something with the driver (e.g. Open, Close, or send IOCTL). These functions are identified by\n  <a href=\"http://msdn.microsoft.com/en-us/library/windows/hardware/ff550710.aspx\" rel=\"nofollow noreferrer\">\n   IRP Major Function Codes\n  </a>\n  .\n </p>\n <p>\n  In the case of ioctls sent by\n  <code>\n   DeviceIoControl\n  </code>\n  , the\n  <a href=\"http://msdn.microsoft.com/en-us/library/windows/hardware/ff550744.aspx\" rel=\"nofollow noreferrer\">\n   <code>\n    IRP_MJ_DEVICE_CONTROL\n   </code>\n  </a>\n  function is called. This function is called for\n  <em>\n   any\n  </em>\n  ioctl.  Now to determine which\n  <code>\n   dwIoControlCode\n  </code>\n  was passed to\n  <code>\n   DeviceIoControl\n  </code>\n  , the ioctl-handling function will look at\n  <code>\n   Parameters.DeviceIoControl.IoControlCode\n  </code>\n  .\n </p>\n <p>\n  From this value, there is often a switch-statement which selects different behavior depending on the control code.\n </p>\n <hr/>\n <p>\n  So first, you want to load up the\n  <code>\n   .sys\n  </code>\n  driver into IDA. The function that IDA marks as\n  <code>\n   DriverEntry\n  </code>\n  is really a wrapper generated by the DDK. The real\n  <code>\n   DriverEntry\n  </code>\n  is usually\n  <code>\n   jmp\n  </code>\n  'd to at the end of this stub.\n </p>\n <p>\n  In the real\n  <code>\n   DriverEntry\n  </code>\n  , you'll want to locate where the\n  <code>\n   MajorFunction\n  </code>\n  entries are populated. It might look something like this:\n </p>\n <p>\n  <img alt=\"enter image description here\" src=\"https://i.sstatic.net/BWlFv.png\"/>\n </p>\n</div>\n</body></html>",
            "votes": "9",
            "user": "Jonathon Reinhart",
            "time": "Mar 26, 2014 at 5:49",
            "is_accepted": false,
            "comments": []
        }
    ]
}