{
    "title": "UTF8, UTF16 encoding string search",
    "link": "https://reverseengineering.stackexchange.com/questions/21937/utf8-utf16-encoding-string-search",
    "content": "I want to search for a string written in Georgian from within x64dbg. It shows me spaces except them.. \nP.S I found this github repository but, I don't know how to install the plugin in the debugger... it seems to be a different kind of plugin.. please help, I need it like air.. thanks!\n",
    "votes": "1",
    "answers": 0,
    "views": "471",
    "tags": [
        "debuggers",
        "x64dbg"
    ],
    "user": "Nikoloz Chitashvili",
    "time": "Aug 20, 2019 at 13:30",
    "comments": [
        {
            "user": "bart1e",
            "text": "I think that plugin doesn't do what you want. It is used rather for string comparison while tracing. Basically, you assign each string some numeric value and then you can compare it as you would compare two numbers. However, if it is what you want, let me know and I'll show you how to install it.\n",
            "time": null
        },
        {
            "user": "mrexodia",
            "text": "I would appreciate it if you could provide an example executable that show this replacing the text with spaces...\n",
            "time": null
        },
        {
            "user": "Biswapriyo",
            "text": "Alternatively, the string can be searched in hex viewer, for example HxD.\n",
            "time": null
        }
    ],
    "answers_data": []
}